CHANGELOG.rst
LICENSE
MANIFEST.in
README.rst
pyproject.toml
setup.cfg
setup.py
tox.ini
.circleci/config.yml
Mopidy_DefaultPlaylist.egg-info/PKG-INFO
Mopidy_DefaultPlaylist.egg-info/SOURCES.txt
Mopidy_DefaultPlaylist.egg-info/dependency_links.txt
Mopidy_DefaultPlaylist.egg-info/entry_points.txt
Mopidy_DefaultPlaylist.egg-info/not-zip-safe
Mopidy_DefaultPlaylist.egg-info/requires.txt
Mopidy_DefaultPlaylist.egg-info/top_level.txt
mopidy_defaultplaylist/__init__.py
mopidy_defaultplaylist/ext.conf
mopidy_defaultplaylist/frontend.py
tests/__init__.py
tests/test_extension.py