Metadata-Version: 2.1
Name: Mopidy-DefaultPlaylist
Version: 0.1.0
Summary: Sets a default playlist for Mopidy
Home-page: https://github.com/michaelmeer/mopidy-defaultplaylist
Author: Michael Meer
Author-email: michael.meer@gmail.com
License: Apache License, Version 2.0
Platform: UNKNOWN
Classifier: Environment :: No Input/Output (Daemon)
Classifier: Intended Audience :: End Users/Desktop
Classifier: License :: OSI Approved :: Apache Software License
Classifier: Operating System :: OS Independent
Classifier: Programming Language :: Python :: 3
Classifier: Programming Language :: Python :: 3.7
Classifier: Programming Language :: Python :: 3.8
Classifier: Topic :: Multimedia :: Sound/Audio :: Players
Requires-Python: >= 3.7
Provides-Extra: dev
Provides-Extra: lint
Provides-Extra: release
Provides-Extra: test
